{"Timestamp":"2023-01-28T01:22:24.1264038+03:30","Level":"Error","MessageTemplate":"Endpoint Phoenix.RestApi.Controllers.WeatherForecastController.Get (Phoenix.RestApi) contains authorization metadata, but a middleware was not found that supports authorization.\r\nConfigure your application startup by adding app.UseAuthorization() in the application startup code. If there are calls to app.UseRouting() and app.UseEndpoints(...), the call to app.UseAuthorization() must go between them. Request failed with Status Code 200 and Error Id 5eabe7a0-7cc1-4d31-9eb5-13a112ebbdd4.","Properties":{"StackTrace":"   at Microsoft.AspNetCore.Routing.EndpointMiddleware.ThrowMissingAuthMiddlewareException(Endpoint endpoint)\r\n   at Microsoft.AspNetCore.Routing.EndpointMiddleware.Invoke(HttpContext httpContext)\r\n   at Microsoft.AspNetCore.Routing.EndpointRoutingMiddleware.Invoke(HttpContext httpContext)\r\n   at Phoenix.Infrastructure.Middleware.ExceptionMiddleware.InvokeAsync(HttpContext context, RequestDelegate next) in D:\\MyArchitecture\\Main\\dotnet-phoenix-clean-architecture\\src\\Phoenix.Infrastructure\\Middleware\\ExceptionMiddleware.cs:line 33","ErrorId":"5eabe7a0-7cc1-4d31-9eb5-13a112ebbdd4","UserEmail":"","RequestId":"0HMO0M2QEP1BQ:00000008","RequestPath":"/api/v1/tests","ConnectionId":"0HMO0M2QEP1BQ","MachineName":"LAPTOP-TSMJLLUF","ProcessId":23760,"ThreadId":14,"Application":"Phoenix.Web"}}
{"Timestamp":"2023-01-28T01:23:23.6459912+03:30","Level":"Information","MessageTemplate":"Applying Root Migrations ...","Properties":{"SourceContext":"Phoenix.Infrastructure.Persistence.Initialization.DatabaseInitializer","MachineName":"LAPTOP-TSMJLLUF","ProcessId":30384,"ThreadId":14,"Application":"Phoenix.Web"}}
{"Timestamp":"2023-01-28T01:23:26.8288662+03:30","Level":"Information","MessageTemplate":"\r\n*******  | DataBase Migration Updated Successfully | *******\r\n","Properties":{"SourceContext":"Phoenix.Infrastructure.Persistence.Initialization.DatabaseInitializer","MachineName":"LAPTOP-TSMJLLUF","ProcessId":30384,"ThreadId":14,"Application":"Phoenix.Web"}}
{"Timestamp":"2023-01-28T01:23:27.2004407+03:30","Level":"Information","MessageTemplate":"Now listening on: {address}","Properties":{"address":"http://localhost:5000","EventId":{"Id":14,"Name":"ListeningOnAddress"},"SourceContext":"Microsoft.Hosting.Lifetime","MachineName":"LAPTOP-TSMJLLUF","ProcessId":30384,"ThreadId":14,"Application":"Phoenix.Web"}}
{"Timestamp":"2023-01-28T01:23:27.2018815+03:30","Level":"Information","MessageTemplate":"Application started. Press Ctrl+C to shut down.","Properties":{"SourceContext":"Microsoft.Hosting.Lifetime","MachineName":"LAPTOP-TSMJLLUF","ProcessId":30384,"ThreadId":14,"Application":"Phoenix.Web"}}
{"Timestamp":"2023-01-28T01:23:27.2020660+03:30","Level":"Information","MessageTemplate":"Hosting environment: {envName}","Properties":{"envName":"Development","SourceContext":"Microsoft.Hosting.Lifetime","MachineName":"LAPTOP-TSMJLLUF","ProcessId":30384,"ThreadId":14,"Application":"Phoenix.Web"}}
{"Timestamp":"2023-01-28T01:23:27.2021543+03:30","Level":"Information","MessageTemplate":"Content root path: {contentRoot}","Properties":{"contentRoot":"D:\\MyArchitecture\\Main\\dotnet-phoenix-clean-architecture\\src\\Phoenix.RestApi\\","SourceContext":"Microsoft.Hosting.Lifetime","MachineName":"LAPTOP-TSMJLLUF","ProcessId":30384,"ThreadId":14,"Application":"Phoenix.Web"}}
{"Timestamp":"2023-01-28T01:25:27.5973162+03:30","Level":"Information","MessageTemplate":"Applying Root Migrations ...","Properties":{"SourceContext":"Phoenix.Infrastructure.Persistence.Initialization.DatabaseInitializer","MachineName":"LAPTOP-TSMJLLUF","ProcessId":32976,"ThreadId":13,"Application":"Phoenix.Web"}}
{"Timestamp":"2023-01-28T01:25:30.7548026+03:30","Level":"Information","MessageTemplate":"\r\n*******  | DataBase Migration Updated Successfully | *******\r\n","Properties":{"SourceContext":"Phoenix.Infrastructure.Persistence.Initialization.DatabaseInitializer","MachineName":"LAPTOP-TSMJLLUF","ProcessId":32976,"ThreadId":13,"Application":"Phoenix.Web"}}
{"Timestamp":"2023-01-28T01:25:31.1473624+03:30","Level":"Information","MessageTemplate":"Now listening on: {address}","Properties":{"address":"http://localhost:5000","EventId":{"Id":14,"Name":"ListeningOnAddress"},"SourceContext":"Microsoft.Hosting.Lifetime","MachineName":"LAPTOP-TSMJLLUF","ProcessId":32976,"ThreadId":13,"Application":"Phoenix.Web"}}
{"Timestamp":"2023-01-28T01:25:31.1491880+03:30","Level":"Information","MessageTemplate":"Application started. Press Ctrl+C to shut down.","Properties":{"SourceContext":"Microsoft.Hosting.Lifetime","MachineName":"LAPTOP-TSMJLLUF","ProcessId":32976,"ThreadId":13,"Application":"Phoenix.Web"}}
{"Timestamp":"2023-01-28T01:25:31.1494345+03:30","Level":"Information","MessageTemplate":"Hosting environment: {envName}","Properties":{"envName":"Development","SourceContext":"Microsoft.Hosting.Lifetime","MachineName":"LAPTOP-TSMJLLUF","ProcessId":32976,"ThreadId":13,"Application":"Phoenix.Web"}}
{"Timestamp":"2023-01-28T01:25:31.1495534+03:30","Level":"Information","MessageTemplate":"Content root path: {contentRoot}","Properties":{"contentRoot":"D:\\MyArchitecture\\Main\\dotnet-phoenix-clean-architecture\\src\\Phoenix.RestApi\\","SourceContext":"Microsoft.Hosting.Lifetime","MachineName":"LAPTOP-TSMJLLUF","ProcessId":32976,"ThreadId":13,"Application":"Phoenix.Web"}}
{"Timestamp":"2023-01-28T01:31:05.2894032+03:30","Level":"Information","MessageTemplate":"Applying Root Migrations ...","Properties":{"SourceContext":"Phoenix.Infrastructure.Persistence.Initialization.DatabaseInitializer","MachineName":"LAPTOP-TSMJLLUF","ProcessId":32324,"ThreadId":13,"Application":"Phoenix.Web"}}
{"Timestamp":"2023-01-28T01:31:09.4614119+03:30","Level":"Information","MessageTemplate":"\r\n*******  | DataBase Migration Updated Successfully | *******\r\n","Properties":{"SourceContext":"Phoenix.Infrastructure.Persistence.Initialization.DatabaseInitializer","MachineName":"LAPTOP-TSMJLLUF","ProcessId":32324,"ThreadId":13,"Application":"Phoenix.Web"}}
{"Timestamp":"2023-01-28T01:31:10.2613868+03:30","Level":"Information","MessageTemplate":"Now listening on: {address}","Properties":{"address":"http://localhost:5000","EventId":{"Id":14,"Name":"ListeningOnAddress"},"SourceContext":"Microsoft.Hosting.Lifetime","MachineName":"LAPTOP-TSMJLLUF","ProcessId":32324,"ThreadId":13,"Application":"Phoenix.Web"}}
{"Timestamp":"2023-01-28T01:31:10.2626287+03:30","Level":"Information","MessageTemplate":"Application started. Press Ctrl+C to shut down.","Properties":{"SourceContext":"Microsoft.Hosting.Lifetime","MachineName":"LAPTOP-TSMJLLUF","ProcessId":32324,"ThreadId":13,"Application":"Phoenix.Web"}}
{"Timestamp":"2023-01-28T01:31:10.2627983+03:30","Level":"Information","MessageTemplate":"Hosting environment: {envName}","Properties":{"envName":"Development","SourceContext":"Microsoft.Hosting.Lifetime","MachineName":"LAPTOP-TSMJLLUF","ProcessId":32324,"ThreadId":13,"Application":"Phoenix.Web"}}
{"Timestamp":"2023-01-28T01:31:10.2628943+03:30","Level":"Information","MessageTemplate":"Content root path: {contentRoot}","Properties":{"contentRoot":"D:\\MyArchitecture\\Main\\dotnet-phoenix-clean-architecture\\src\\Phoenix.RestApi\\","SourceContext":"Microsoft.Hosting.Lifetime","MachineName":"LAPTOP-TSMJLLUF","ProcessId":32324,"ThreadId":13,"Application":"Phoenix.Web"}}
{"Timestamp":"2023-01-28T01:45:04.9142864+03:30","Level":"Information","MessageTemplate":"Applying Root Migrations ...","Properties":{"SourceContext":"Phoenix.Infrastructure.Persistence.Initialization.DatabaseInitializer","MachineName":"LAPTOP-TSMJLLUF","ProcessId":24648,"ThreadId":13,"Application":"Phoenix.Web"}}
{"Timestamp":"2023-01-28T01:45:09.4721364+03:30","Level":"Information","MessageTemplate":"\r\n*******  | DataBase Migration Updated Successfully | *******\r\n","Properties":{"SourceContext":"Phoenix.Infrastructure.Persistence.Initialization.DatabaseInitializer","MachineName":"LAPTOP-TSMJLLUF","ProcessId":24648,"ThreadId":13,"Application":"Phoenix.Web"}}
{"Timestamp":"2023-01-28T01:45:10.2328292+03:30","Level":"Information","MessageTemplate":"Now listening on: {address}","Properties":{"address":"http://localhost:5000","EventId":{"Id":14,"Name":"ListeningOnAddress"},"SourceContext":"Microsoft.Hosting.Lifetime","MachineName":"LAPTOP-TSMJLLUF","ProcessId":24648,"ThreadId":13,"Application":"Phoenix.Web"}}
{"Timestamp":"2023-01-28T01:45:10.2369799+03:30","Level":"Information","MessageTemplate":"Application started. Press Ctrl+C to shut down.","Properties":{"SourceContext":"Microsoft.Hosting.Lifetime","MachineName":"LAPTOP-TSMJLLUF","ProcessId":24648,"ThreadId":13,"Application":"Phoenix.Web"}}
{"Timestamp":"2023-01-28T01:45:10.2375162+03:30","Level":"Information","MessageTemplate":"Hosting environment: {envName}","Properties":{"envName":"Development","SourceContext":"Microsoft.Hosting.Lifetime","MachineName":"LAPTOP-TSMJLLUF","ProcessId":24648,"ThreadId":13,"Application":"Phoenix.Web"}}
{"Timestamp":"2023-01-28T01:45:10.2378348+03:30","Level":"Information","MessageTemplate":"Content root path: {contentRoot}","Properties":{"contentRoot":"D:\\MyArchitecture\\Main\\dotnet-phoenix-clean-architecture\\src\\Phoenix.RestApi\\","SourceContext":"Microsoft.Hosting.Lifetime","MachineName":"LAPTOP-TSMJLLUF","ProcessId":24648,"ThreadId":13,"Application":"Phoenix.Web"}}
{"Timestamp":"2023-01-28T01:45:34.9746252+03:30","Level":"Warning","MessageTemplate":"{State:l}","Properties":{"State":"Stopping the server due to DomainUnload or ProcessExit event...","SourceContext":"Hangfire.Server.BackgroundProcessingServer","MachineName":"LAPTOP-TSMJLLUF","ProcessId":24648,"ThreadId":2,"Application":"Phoenix.Web"},"Renderings":{"State":[{"Format":"l","Rendering":"Stopping the server due to DomainUnload or ProcessExit event..."}]}}
{"Timestamp":"2023-01-28T01:45:34.9774937+03:30","Level":"Warning","MessageTemplate":"{State:l}","Properties":{"State":"Server c355b56d-7162-4d98-a697-d08f68632bfa caught shutdown signal...","SourceContext":"Hangfire.Server.BackgroundServerProcess","MachineName":"LAPTOP-TSMJLLUF","ProcessId":24648,"ThreadId":2,"Application":"Phoenix.Web"},"Renderings":{"State":[{"Format":"l","Rendering":"Server c355b56d-7162-4d98-a697-d08f68632bfa caught shutdown signal..."}]}}
{"Timestamp":"2023-01-28T01:45:34.9912579+03:30","Level":"Warning","MessageTemplate":"{State:l}","Properties":{"State":"Server c355b56d-7162-4d98-a697-d08f68632bfa stopped non-gracefully due to ServerWatchdog, ServerJobCancellationWatcher, ExpirationManager, CountersAggregator, SqlServerHeartbeatProcess, Worker, DelayedJobScheduler, RecurringJobScheduler. Outstanding work on those dispatchers could be aborted, and there can be delays in background processing. This server instance will be incorrectly shown as active for a while. To avoid non-graceful shutdowns, investigate what prevents from stopping gracefully and add CancellationToken support for those methods.","SourceContext":"Hangfire.Server.BackgroundServerProcess","MachineName":"LAPTOP-TSMJLLUF","ProcessId":24648,"ThreadId":18,"Application":"Phoenix.Web"},"Renderings":{"State":[{"Format":"l","Rendering":"Server c355b56d-7162-4d98-a697-d08f68632bfa stopped non-gracefully due to ServerWatchdog, ServerJobCancellationWatcher, ExpirationManager, CountersAggregator, SqlServerHeartbeatProcess, Worker, DelayedJobScheduler, RecurringJobScheduler. Outstanding work on those dispatchers could be aborted, and there can be delays in background processing. This server instance will be incorrectly shown as active for a while. To avoid non-graceful shutdowns, investigate what prevents from stopping gracefully and add CancellationToken support for those methods."}]}}
{"Timestamp":"2023-01-28T01:49:53.6800344+03:30","Level":"Information","MessageTemplate":"Applying Root Migrations ...","Properties":{"SourceContext":"Phoenix.Infrastructure.Persistence.Initialization.DatabaseInitializer","MachineName":"LAPTOP-TSMJLLUF","ProcessId":4676,"ThreadId":9,"Application":"Phoenix.Web"}}
{"Timestamp":"2023-01-28T01:49:57.2906755+03:30","Level":"Information","MessageTemplate":"\r\n*******  | DataBase Migration Updated Successfully | *******\r\n","Properties":{"SourceContext":"Phoenix.Infrastructure.Persistence.Initialization.DatabaseInitializer","MachineName":"LAPTOP-TSMJLLUF","ProcessId":4676,"ThreadId":9,"Application":"Phoenix.Web"}}
{"Timestamp":"2023-01-28T01:49:58.3195322+03:30","Level":"Information","MessageTemplate":"Now listening on: {address}","Properties":{"address":"http://localhost:5000","EventId":{"Id":14,"Name":"ListeningOnAddress"},"SourceContext":"Microsoft.Hosting.Lifetime","MachineName":"LAPTOP-TSMJLLUF","ProcessId":4676,"ThreadId":9,"Application":"Phoenix.Web"}}
{"Timestamp":"2023-01-28T01:49:58.3216395+03:30","Level":"Information","MessageTemplate":"Application started. Press Ctrl+C to shut down.","Properties":{"SourceContext":"Microsoft.Hosting.Lifetime","MachineName":"LAPTOP-TSMJLLUF","ProcessId":4676,"ThreadId":9,"Application":"Phoenix.Web"}}
{"Timestamp":"2023-01-28T01:49:58.3219948+03:30","Level":"Information","MessageTemplate":"Hosting environment: {envName}","Properties":{"envName":"Development","SourceContext":"Microsoft.Hosting.Lifetime","MachineName":"LAPTOP-TSMJLLUF","ProcessId":4676,"ThreadId":9,"Application":"Phoenix.Web"}}
{"Timestamp":"2023-01-28T01:49:58.3221301+03:30","Level":"Information","MessageTemplate":"Content root path: {contentRoot}","Properties":{"contentRoot":"D:\\MyArchitecture\\Main\\dotnet-phoenix-clean-architecture\\src\\Phoenix.RestApi\\","SourceContext":"Microsoft.Hosting.Lifetime","MachineName":"LAPTOP-TSMJLLUF","ProcessId":4676,"ThreadId":9,"Application":"Phoenix.Web"}}
{"Timestamp":"2023-01-28T17:18:16.3918959+03:30","Level":"Information","MessageTemplate":"Applying Root Migrations ...","Properties":{"SourceContext":"Phoenix.Infrastructure.Persistence.Initialization.DatabaseInitializer","MachineName":"LAPTOP-TSMJLLUF","ProcessId":22344,"ThreadId":13,"Application":"Phoenix.Web"}}
{"Timestamp":"2023-01-28T17:18:20.1850589+03:30","Level":"Information","MessageTemplate":"\r\n*******  | DataBase Migration Updated Successfully | *******\r\n","Properties":{"SourceContext":"Phoenix.Infrastructure.Persistence.Initialization.DatabaseInitializer","MachineName":"LAPTOP-TSMJLLUF","ProcessId":22344,"ThreadId":13,"Application":"Phoenix.Web"}}
{"Timestamp":"2023-01-28T17:18:21.8099081+03:30","Level":"Information","MessageTemplate":"Now listening on: {address}","Properties":{"address":"http://localhost:5000","EventId":{"Id":14,"Name":"ListeningOnAddress"},"SourceContext":"Microsoft.Hosting.Lifetime","MachineName":"LAPTOP-TSMJLLUF","ProcessId":22344,"ThreadId":13,"Application":"Phoenix.Web"}}
{"Timestamp":"2023-01-28T17:18:21.8129012+03:30","Level":"Information","MessageTemplate":"Application started. Press Ctrl+C to shut down.","Properties":{"SourceContext":"Microsoft.Hosting.Lifetime","MachineName":"LAPTOP-TSMJLLUF","ProcessId":22344,"ThreadId":13,"Application":"Phoenix.Web"}}
{"Timestamp":"2023-01-28T17:18:21.8134128+03:30","Level":"Information","MessageTemplate":"Hosting environment: {envName}","Properties":{"envName":"Development","SourceContext":"Microsoft.Hosting.Lifetime","MachineName":"LAPTOP-TSMJLLUF","ProcessId":22344,"ThreadId":13,"Application":"Phoenix.Web"}}
{"Timestamp":"2023-01-28T17:18:21.8136739+03:30","Level":"Information","MessageTemplate":"Content root path: {contentRoot}","Properties":{"contentRoot":"D:\\MyArchitecture\\Main\\dotnet-phoenix-clean-architecture\\src\\Phoenix.RestApi\\","SourceContext":"Microsoft.Hosting.Lifetime","MachineName":"LAPTOP-TSMJLLUF","ProcessId":22344,"ThreadId":13,"Application":"Phoenix.Web"}}
{"Timestamp":"2023-01-28T19:04:31.7309800+03:30","Level":"Information","MessageTemplate":"Applying Root Migrations ...","Properties":{"SourceContext":"Phoenix.Infrastructure.Persistence.Initialization.DatabaseInitializer","MachineName":"LAPTOP-TSMJLLUF","ProcessId":5572,"ThreadId":13,"Application":"Phoenix.Web"}}
{"Timestamp":"2023-01-28T19:04:35.3946120+03:30","Level":"Information","MessageTemplate":"\r\n*******  | DataBase Migration Updated Successfully | *******\r\n","Properties":{"SourceContext":"Phoenix.Infrastructure.Persistence.Initialization.DatabaseInitializer","MachineName":"LAPTOP-TSMJLLUF","ProcessId":5572,"ThreadId":13,"Application":"Phoenix.Web"}}
{"Timestamp":"2023-01-28T19:04:36.5948336+03:30","Level":"Information","MessageTemplate":"Now listening on: {address}","Properties":{"address":"http://localhost:5000","EventId":{"Id":14,"Name":"ListeningOnAddress"},"SourceContext":"Microsoft.Hosting.Lifetime","MachineName":"LAPTOP-TSMJLLUF","ProcessId":5572,"ThreadId":13,"Application":"Phoenix.Web"}}
{"Timestamp":"2023-01-28T19:04:36.5962692+03:30","Level":"Information","MessageTemplate":"Application started. Press Ctrl+C to shut down.","Properties":{"SourceContext":"Microsoft.Hosting.Lifetime","MachineName":"LAPTOP-TSMJLLUF","ProcessId":5572,"ThreadId":13,"Application":"Phoenix.Web"}}
{"Timestamp":"2023-01-28T19:04:36.5964835+03:30","Level":"Information","MessageTemplate":"Hosting environment: {envName}","Properties":{"envName":"Development","SourceContext":"Microsoft.Hosting.Lifetime","MachineName":"LAPTOP-TSMJLLUF","ProcessId":5572,"ThreadId":13,"Application":"Phoenix.Web"}}
{"Timestamp":"2023-01-28T19:04:36.5966486+03:30","Level":"Information","MessageTemplate":"Content root path: {contentRoot}","Properties":{"contentRoot":"D:\\MyArchitecture\\Main\\dotnet-phoenix-clean-architecture\\src\\Phoenix.RestApi\\","SourceContext":"Microsoft.Hosting.Lifetime","MachineName":"LAPTOP-TSMJLLUF","ProcessId":5572,"ThreadId":13,"Application":"Phoenix.Web"}}
{"Timestamp":"2023-01-28T19:43:56.1285258+03:30","Level":"Information","MessageTemplate":"Applying Root Migrations ...","Properties":{"SourceContext":"Phoenix.Infrastructure.Persistence.Initialization.DatabaseInitializer","MachineName":"LAPTOP-TSMJLLUF","ProcessId":15908,"ThreadId":12,"Application":"Phoenix.Web"}}
{"Timestamp":"2023-01-28T19:43:59.8556245+03:30","Level":"Information","MessageTemplate":"\r\n*******  | DataBase Migration Updated Successfully | *******\r\n","Properties":{"SourceContext":"Phoenix.Infrastructure.Persistence.Initialization.DatabaseInitializer","MachineName":"LAPTOP-TSMJLLUF","ProcessId":15908,"ThreadId":12,"Application":"Phoenix.Web"}}
{"Timestamp":"2023-01-28T19:44:01.2546135+03:30","Level":"Information","MessageTemplate":"Now listening on: {address}","Properties":{"address":"http://localhost:5000","EventId":{"Id":14,"Name":"ListeningOnAddress"},"SourceContext":"Microsoft.Hosting.Lifetime","MachineName":"LAPTOP-TSMJLLUF","ProcessId":15908,"ThreadId":12,"Application":"Phoenix.Web"}}
{"Timestamp":"2023-01-28T19:44:01.2565342+03:30","Level":"Information","MessageTemplate":"Application started. Press Ctrl+C to shut down.","Properties":{"SourceContext":"Microsoft.Hosting.Lifetime","MachineName":"LAPTOP-TSMJLLUF","ProcessId":15908,"ThreadId":12,"Application":"Phoenix.Web"}}
{"Timestamp":"2023-01-28T19:44:01.2569924+03:30","Level":"Information","MessageTemplate":"Hosting environment: {envName}","Properties":{"envName":"Development","SourceContext":"Microsoft.Hosting.Lifetime","MachineName":"LAPTOP-TSMJLLUF","ProcessId":15908,"ThreadId":12,"Application":"Phoenix.Web"}}
{"Timestamp":"2023-01-28T19:44:01.2572352+03:30","Level":"Information","MessageTemplate":"Content root path: {contentRoot}","Properties":{"contentRoot":"D:\\MyArchitecture\\Main\\dotnet-phoenix-clean-architecture\\src\\Phoenix.RestApi\\","SourceContext":"Microsoft.Hosting.Lifetime","MachineName":"LAPTOP-TSMJLLUF","ProcessId":15908,"ThreadId":12,"Application":"Phoenix.Web"}}
{"Timestamp":"2023-01-28T19:52:21.0768516+03:30","Level":"Information","MessageTemplate":"Applying Root Migrations ...","Properties":{"SourceContext":"Phoenix.Infrastructure.Persistence.Initialization.DatabaseInitializer","MachineName":"LAPTOP-TSMJLLUF","ProcessId":5412,"ThreadId":9,"Application":"Phoenix.Web"}}
{"Timestamp":"2023-01-28T19:52:24.3340624+03:30","Level":"Information","MessageTemplate":"\r\n*******  | DataBase Migration Updated Successfully | *******\r\n","Properties":{"SourceContext":"Phoenix.Infrastructure.Persistence.Initialization.DatabaseInitializer","MachineName":"LAPTOP-TSMJLLUF","ProcessId":5412,"ThreadId":9,"Application":"Phoenix.Web"}}
{"Timestamp":"2023-01-28T19:52:25.0511610+03:30","Level":"Information","MessageTemplate":"Now listening on: {address}","Properties":{"address":"http://localhost:5000","EventId":{"Id":14,"Name":"ListeningOnAddress"},"SourceContext":"Microsoft.Hosting.Lifetime","MachineName":"LAPTOP-TSMJLLUF","ProcessId":5412,"ThreadId":9,"Application":"Phoenix.Web"}}
{"Timestamp":"2023-01-28T19:52:25.0526137+03:30","Level":"Information","MessageTemplate":"Application started. Press Ctrl+C to shut down.","Properties":{"SourceContext":"Microsoft.Hosting.Lifetime","MachineName":"LAPTOP-TSMJLLUF","ProcessId":5412,"ThreadId":9,"Application":"Phoenix.Web"}}
{"Timestamp":"2023-01-28T19:52:25.0527697+03:30","Level":"Information","MessageTemplate":"Hosting environment: {envName}","Properties":{"envName":"Development","SourceContext":"Microsoft.Hosting.Lifetime","MachineName":"LAPTOP-TSMJLLUF","ProcessId":5412,"ThreadId":9,"Application":"Phoenix.Web"}}
{"Timestamp":"2023-01-28T19:52:25.0528805+03:30","Level":"Information","MessageTemplate":"Content root path: {contentRoot}","Properties":{"contentRoot":"D:\\MyArchitecture\\Main\\dotnet-phoenix-clean-architecture\\src\\Phoenix.RestApi\\","SourceContext":"Microsoft.Hosting.Lifetime","MachineName":"LAPTOP-TSMJLLUF","ProcessId":5412,"ThreadId":9,"Application":"Phoenix.Web"}}
{"Timestamp":"2023-01-28T19:53:29.4969763+03:30","Level":"Information","MessageTemplate":"Applying Root Migrations ...","Properties":{"SourceContext":"Phoenix.Infrastructure.Persistence.Initialization.DatabaseInitializer","MachineName":"LAPTOP-TSMJLLUF","ProcessId":19044,"ThreadId":13,"Application":"Phoenix.Web"}}
{"Timestamp":"2023-01-28T19:53:32.7372507+03:30","Level":"Information","MessageTemplate":"\r\n*******  | DataBase Migration Updated Successfully | *******\r\n","Properties":{"SourceContext":"Phoenix.Infrastructure.Persistence.Initialization.DatabaseInitializer","MachineName":"LAPTOP-TSMJLLUF","ProcessId":19044,"ThreadId":13,"Application":"Phoenix.Web"}}
{"Timestamp":"2023-01-28T19:53:33.3242817+03:30","Level":"Information","MessageTemplate":"Now listening on: {address}","Properties":{"address":"http://localhost:5000","EventId":{"Id":14,"Name":"ListeningOnAddress"},"SourceContext":"Microsoft.Hosting.Lifetime","MachineName":"LAPTOP-TSMJLLUF","ProcessId":19044,"ThreadId":13,"Application":"Phoenix.Web"}}
{"Timestamp":"2023-01-28T19:53:33.3257429+03:30","Level":"Information","MessageTemplate":"Application started. Press Ctrl+C to shut down.","Properties":{"SourceContext":"Microsoft.Hosting.Lifetime","MachineName":"LAPTOP-TSMJLLUF","ProcessId":19044,"ThreadId":13,"Application":"Phoenix.Web"}}
{"Timestamp":"2023-01-28T19:53:33.3260433+03:30","Level":"Information","MessageTemplate":"Hosting environment: {envName}","Properties":{"envName":"Development","SourceContext":"Microsoft.Hosting.Lifetime","MachineName":"LAPTOP-TSMJLLUF","ProcessId":19044,"ThreadId":13,"Application":"Phoenix.Web"}}
{"Timestamp":"2023-01-28T19:53:33.3261970+03:30","Level":"Information","MessageTemplate":"Content root path: {contentRoot}","Properties":{"contentRoot":"D:\\MyArchitecture\\Main\\dotnet-phoenix-clean-architecture\\src\\Phoenix.RestApi\\","SourceContext":"Microsoft.Hosting.Lifetime","MachineName":"LAPTOP-TSMJLLUF","ProcessId":19044,"ThreadId":13,"Application":"Phoenix.Web"}}
{"Timestamp":"2023-01-28T19:54:29.9693183+03:30","Level":"Information","MessageTemplate":"Applying Root Migrations ...","Properties":{"SourceContext":"Phoenix.Infrastructure.Persistence.Initialization.DatabaseInitializer","MachineName":"LAPTOP-TSMJLLUF","ProcessId":14912,"ThreadId":13,"Application":"Phoenix.Web"}}
{"Timestamp":"2023-01-28T19:54:33.4222661+03:30","Level":"Information","MessageTemplate":"\r\n*******  | DataBase Migration Updated Successfully | *******\r\n","Properties":{"SourceContext":"Phoenix.Infrastructure.Persistence.Initialization.DatabaseInitializer","MachineName":"LAPTOP-TSMJLLUF","ProcessId":14912,"ThreadId":13,"Application":"Phoenix.Web"}}
{"Timestamp":"2023-01-28T19:54:34.0665053+03:30","Level":"Information","MessageTemplate":"Now listening on: {address}","Properties":{"address":"http://localhost:5000","EventId":{"Id":14,"Name":"ListeningOnAddress"},"SourceContext":"Microsoft.Hosting.Lifetime","MachineName":"LAPTOP-TSMJLLUF","ProcessId":14912,"ThreadId":13,"Application":"Phoenix.Web"}}
{"Timestamp":"2023-01-28T19:54:34.0690815+03:30","Level":"Information","MessageTemplate":"Application started. Press Ctrl+C to shut down.","Properties":{"SourceContext":"Microsoft.Hosting.Lifetime","MachineName":"LAPTOP-TSMJLLUF","ProcessId":14912,"ThreadId":13,"Application":"Phoenix.Web"}}
{"Timestamp":"2023-01-28T19:54:34.0693823+03:30","Level":"Information","MessageTemplate":"Hosting environment: {envName}","Properties":{"envName":"Development","SourceContext":"Microsoft.Hosting.Lifetime","MachineName":"LAPTOP-TSMJLLUF","ProcessId":14912,"ThreadId":13,"Application":"Phoenix.Web"}}
{"Timestamp":"2023-01-28T19:54:34.0695628+03:30","Level":"Information","MessageTemplate":"Content root path: {contentRoot}","Properties":{"contentRoot":"D:\\MyArchitecture\\Main\\dotnet-phoenix-clean-architecture\\src\\Phoenix.RestApi\\","SourceContext":"Microsoft.Hosting.Lifetime","MachineName":"LAPTOP-TSMJLLUF","ProcessId":14912,"ThreadId":13,"Application":"Phoenix.Web"}}
{"Timestamp":"2023-01-28T19:59:09.6074021+03:30","Level":"Information","MessageTemplate":"Applying Root Migrations ...","Properties":{"SourceContext":"Phoenix.Infrastructure.Persistence.Initialization.DatabaseInitializer","MachineName":"LAPTOP-TSMJLLUF","ProcessId":11284,"ThreadId":13,"Application":"Phoenix.Web"}}
{"Timestamp":"2023-01-28T19:59:13.0601600+03:30","Level":"Information","MessageTemplate":"\r\n*******  | DataBase Migration Updated Successfully | *******\r\n","Properties":{"SourceContext":"Phoenix.Infrastructure.Persistence.Initialization.DatabaseInitializer","MachineName":"LAPTOP-TSMJLLUF","ProcessId":11284,"ThreadId":13,"Application":"Phoenix.Web"}}
{"Timestamp":"2023-01-28T19:59:13.7213900+03:30","Level":"Information","MessageTemplate":"Now listening on: {address}","Properties":{"address":"http://localhost:5000","EventId":{"Id":14,"Name":"ListeningOnAddress"},"SourceContext":"Microsoft.Hosting.Lifetime","MachineName":"LAPTOP-TSMJLLUF","ProcessId":11284,"ThreadId":13,"Application":"Phoenix.Web"}}
{"Timestamp":"2023-01-28T19:59:13.7225951+03:30","Level":"Information","MessageTemplate":"Application started. Press Ctrl+C to shut down.","Properties":{"SourceContext":"Microsoft.Hosting.Lifetime","MachineName":"LAPTOP-TSMJLLUF","ProcessId":11284,"ThreadId":13,"Application":"Phoenix.Web"}}
{"Timestamp":"2023-01-28T19:59:13.7227737+03:30","Level":"Information","MessageTemplate":"Hosting environment: {envName}","Properties":{"envName":"Development","SourceContext":"Microsoft.Hosting.Lifetime","MachineName":"LAPTOP-TSMJLLUF","ProcessId":11284,"ThreadId":13,"Application":"Phoenix.Web"}}
{"Timestamp":"2023-01-28T19:59:13.7228584+03:30","Level":"Information","MessageTemplate":"Content root path: {contentRoot}","Properties":{"contentRoot":"D:\\MyArchitecture\\Main\\dotnet-phoenix-clean-architecture\\src\\Phoenix.RestApi\\","SourceContext":"Microsoft.Hosting.Lifetime","MachineName":"LAPTOP-TSMJLLUF","ProcessId":11284,"ThreadId":13,"Application":"Phoenix.Web"}}
{"Timestamp":"2023-01-28T20:07:40.0636323+03:30","Level":"Information","MessageTemplate":"Applying Root Migrations ...","Properties":{"SourceContext":"Phoenix.Infrastructure.Persistence.Initialization.DatabaseInitializer","MachineName":"LAPTOP-TSMJLLUF","ProcessId":26228,"ThreadId":13,"Application":"Phoenix.Web"}}
{"Timestamp":"2023-01-28T20:07:43.2547317+03:30","Level":"Information","MessageTemplate":"\r\n*******  | DataBase Migration Updated Successfully | *******\r\n","Properties":{"SourceContext":"Phoenix.Infrastructure.Persistence.Initialization.DatabaseInitializer","MachineName":"LAPTOP-TSMJLLUF","ProcessId":26228,"ThreadId":13,"Application":"Phoenix.Web"}}
{"Timestamp":"2023-01-28T20:07:43.7105582+03:30","Level":"Information","MessageTemplate":"Now listening on: {address}","Properties":{"address":"http://localhost:5000","EventId":{"Id":14,"Name":"ListeningOnAddress"},"SourceContext":"Microsoft.Hosting.Lifetime","MachineName":"LAPTOP-TSMJLLUF","ProcessId":26228,"ThreadId":13,"Application":"Phoenix.Web"}}
{"Timestamp":"2023-01-28T20:07:43.7121485+03:30","Level":"Information","MessageTemplate":"Application started. Press Ctrl+C to shut down.","Properties":{"SourceContext":"Microsoft.Hosting.Lifetime","MachineName":"LAPTOP-TSMJLLUF","ProcessId":26228,"ThreadId":13,"Application":"Phoenix.Web"}}
{"Timestamp":"2023-01-28T20:07:43.7123747+03:30","Level":"Information","MessageTemplate":"Hosting environment: {envName}","Properties":{"envName":"Development","SourceContext":"Microsoft.Hosting.Lifetime","MachineName":"LAPTOP-TSMJLLUF","ProcessId":26228,"ThreadId":13,"Application":"Phoenix.Web"}}
{"Timestamp":"2023-01-28T20:07:43.7124630+03:30","Level":"Information","MessageTemplate":"Content root path: {contentRoot}","Properties":{"contentRoot":"D:\\MyArchitecture\\Main\\dotnet-phoenix-clean-architecture\\src\\Phoenix.RestApi\\","SourceContext":"Microsoft.Hosting.Lifetime","MachineName":"LAPTOP-TSMJLLUF","ProcessId":26228,"ThreadId":13,"Application":"Phoenix.Web"}}
{"Timestamp":"2023-01-28T20:17:33.9935244+03:30","Level":"Information","MessageTemplate":"Applying Root Migrations ...","Properties":{"SourceContext":"Phoenix.Infrastructure.Persistence.Initialization.DatabaseInitializer","MachineName":"LAPTOP-TSMJLLUF","ProcessId":13984,"ThreadId":13,"Application":"Phoenix.Web"}}
{"Timestamp":"2023-01-28T20:17:37.3654807+03:30","Level":"Information","MessageTemplate":"\r\n*******  | DataBase Migration Updated Successfully | *******\r\n","Properties":{"SourceContext":"Phoenix.Infrastructure.Persistence.Initialization.DatabaseInitializer","MachineName":"LAPTOP-TSMJLLUF","ProcessId":13984,"ThreadId":13,"Application":"Phoenix.Web"}}
{"Timestamp":"2023-01-28T20:17:37.4944927+03:30","Level":"Fatal","MessageTemplate":"Unhandled exception","Exception":"System.InvalidOperationException: Unable to find the required services. Please add all the required services by calling 'IServiceCollection.AddHealthChecks' inside the call to 'ConfigureServices(...)' in the application startup code.\r\n   at Microsoft.AspNetCore.Builder.HealthCheckEndpointRouteBuilderExtensions.MapHealthChecksCore(IEndpointRouteBuilder endpoints, String pattern, HealthCheckOptions options)\r\n   at Microsoft.AspNetCore.Builder.HealthCheckEndpointRouteBuilderExtensions.MapHealthChecks(IEndpointRouteBuilder endpoints, String pattern)\r\n   at Phoenix.Infrastructure.Startup.<>c.<UseInfrastructure>b__2_0(IEndpointRouteBuilder endpoints) in D:\\MyArchitecture\\Main\\dotnet-phoenix-clean-architecture\\src\\Phoenix.Infrastructure\\Startup.cs:line 112\r\n   at Microsoft.AspNetCore.Builder.EndpointRoutingApplicationBuilderExtensions.UseEndpoints(IApplicationBuilder builder, Action`1 configure)\r\n   at Phoenix.Infrastructure.Startup.UseInfrastructure(IApplicationBuilder builder, IConfiguration config) in D:\\MyArchitecture\\Main\\dotnet-phoenix-clean-architecture\\src\\Phoenix.Infrastructure\\Startup.cs:line 101\r\n   at Program.<Main>$(String[] args) in D:\\MyArchitecture\\Main\\dotnet-phoenix-clean-architecture\\src\\Phoenix.RestApi\\Program.cs:line 38","Properties":{"MachineName":"LAPTOP-TSMJLLUF","ProcessId":13984,"ThreadId":13,"Application":"Phoenix.Web"}}
{"Timestamp":"2023-01-28T20:17:37.8131086+03:30","Level":"Information","MessageTemplate":"Server Shutting down...","Properties":{"MachineName":"LAPTOP-TSMJLLUF","ProcessId":13984,"ThreadId":13,"Application":"Phoenix.Web"}}
{"Timestamp":"2023-01-28T20:18:04.5639605+03:30","Level":"Information","MessageTemplate":"Applying Root Migrations ...","Properties":{"SourceContext":"Phoenix.Infrastructure.Persistence.Initialization.DatabaseInitializer","MachineName":"LAPTOP-TSMJLLUF","ProcessId":18752,"ThreadId":12,"Application":"Phoenix.Web"}}
{"Timestamp":"2023-01-28T20:18:07.7876336+03:30","Level":"Information","MessageTemplate":"\r\n*******  | DataBase Migration Updated Successfully | *******\r\n","Properties":{"SourceContext":"Phoenix.Infrastructure.Persistence.Initialization.DatabaseInitializer","MachineName":"LAPTOP-TSMJLLUF","ProcessId":18752,"ThreadId":12,"Application":"Phoenix.Web"}}
{"Timestamp":"2023-01-28T20:18:08.6147928+03:30","Level":"Information","MessageTemplate":"Now listening on: {address}","Properties":{"address":"http://localhost:5000","EventId":{"Id":14,"Name":"ListeningOnAddress"},"SourceContext":"Microsoft.Hosting.Lifetime","MachineName":"LAPTOP-TSMJLLUF","ProcessId":18752,"ThreadId":12,"Application":"Phoenix.Web"}}
{"Timestamp":"2023-01-28T20:18:08.6187669+03:30","Level":"Information","MessageTemplate":"Application started. Press Ctrl+C to shut down.","Properties":{"SourceContext":"Microsoft.Hosting.Lifetime","MachineName":"LAPTOP-TSMJLLUF","ProcessId":18752,"ThreadId":12,"Application":"Phoenix.Web"}}
{"Timestamp":"2023-01-28T20:18:08.6191314+03:30","Level":"Information","MessageTemplate":"Hosting environment: {envName}","Properties":{"envName":"Development","SourceContext":"Microsoft.Hosting.Lifetime","MachineName":"LAPTOP-TSMJLLUF","ProcessId":18752,"ThreadId":12,"Application":"Phoenix.Web"}}
{"Timestamp":"2023-01-28T20:18:08.6193478+03:30","Level":"Information","MessageTemplate":"Content root path: {contentRoot}","Properties":{"contentRoot":"D:\\MyArchitecture\\Main\\dotnet-phoenix-clean-architecture\\src\\Phoenix.RestApi\\","SourceContext":"Microsoft.Hosting.Lifetime","MachineName":"LAPTOP-TSMJLLUF","ProcessId":18752,"ThreadId":12,"Application":"Phoenix.Web"}}
{"Timestamp":"2023-01-28T20:18:14.8275169+03:30","Level":"Warning","MessageTemplate":"{State:l}","Properties":{"State":"Stopping the server due to DomainUnload or ProcessExit event...","SourceContext":"Hangfire.Server.BackgroundProcessingServer","MachineName":"LAPTOP-TSMJLLUF","ProcessId":18752,"ThreadId":2,"Application":"Phoenix.Web"},"Renderings":{"State":[{"Format":"l","Rendering":"Stopping the server due to DomainUnload or ProcessExit event..."}]}}
{"Timestamp":"2023-01-28T20:18:14.8306357+03:30","Level":"Warning","MessageTemplate":"{State:l}","Properties":{"State":"Server b05b2797-a939-4a55-b1f4-6ca769091e94 caught shutdown signal...","SourceContext":"Hangfire.Server.BackgroundServerProcess","MachineName":"LAPTOP-TSMJLLUF","ProcessId":18752,"ThreadId":2,"Application":"Phoenix.Web"},"Renderings":{"State":[{"Format":"l","Rendering":"Server b05b2797-a939-4a55-b1f4-6ca769091e94 caught shutdown signal..."}]}}
{"Timestamp":"2023-01-28T20:18:14.8365887+03:30","Level":"Warning","MessageTemplate":"{State:l}","Properties":{"State":"Server b05b2797-a939-4a55-b1f4-6ca769091e94 stopped non-gracefully due to ServerWatchdog, ServerJobCancellationWatcher, ExpirationManager, CountersAggregator, SqlServerHeartbeatProcess, Worker, DelayedJobScheduler, RecurringJobScheduler. Outstanding work on those dispatchers could be aborted, and there can be delays in background processing. This server instance will be incorrectly shown as active for a while. To avoid non-graceful shutdowns, investigate what prevents from stopping gracefully and add CancellationToken support for those methods.","SourceContext":"Hangfire.Server.BackgroundServerProcess","MachineName":"LAPTOP-TSMJLLUF","ProcessId":18752,"ThreadId":19,"Application":"Phoenix.Web"},"Renderings":{"State":[{"Format":"l","Rendering":"Server b05b2797-a939-4a55-b1f4-6ca769091e94 stopped non-gracefully due to ServerWatchdog, ServerJobCancellationWatcher, ExpirationManager, CountersAggregator, SqlServerHeartbeatProcess, Worker, DelayedJobScheduler, RecurringJobScheduler. Outstanding work on those dispatchers could be aborted, and there can be delays in background processing. This server instance will be incorrectly shown as active for a while. To avoid non-graceful shutdowns, investigate what prevents from stopping gracefully and add CancellationToken support for those methods."}]}}
{"Timestamp":"2023-01-28T20:19:52.9200674+03:30","Level":"Information","MessageTemplate":"Applying Root Migrations ...","Properties":{"SourceContext":"Phoenix.Infrastructure.Persistence.Initialization.DatabaseInitializer","MachineName":"LAPTOP-TSMJLLUF","ProcessId":9164,"ThreadId":13,"Application":"Phoenix.Web"}}
{"Timestamp":"2023-01-28T20:19:56.1847998+03:30","Level":"Information","MessageTemplate":"\r\n*******  | DataBase Migration Updated Successfully | *******\r\n","Properties":{"SourceContext":"Phoenix.Infrastructure.Persistence.Initialization.DatabaseInitializer","MachineName":"LAPTOP-TSMJLLUF","ProcessId":9164,"ThreadId":13,"Application":"Phoenix.Web"}}
{"Timestamp":"2023-01-28T20:19:56.8892881+03:30","Level":"Information","MessageTemplate":"Now listening on: {address}","Properties":{"address":"http://localhost:5000","EventId":{"Id":14,"Name":"ListeningOnAddress"},"SourceContext":"Microsoft.Hosting.Lifetime","MachineName":"LAPTOP-TSMJLLUF","ProcessId":9164,"ThreadId":13,"Application":"Phoenix.Web"}}
{"Timestamp":"2023-01-28T20:19:56.8927871+03:30","Level":"Information","MessageTemplate":"Application started. Press Ctrl+C to shut down.","Properties":{"SourceContext":"Microsoft.Hosting.Lifetime","MachineName":"LAPTOP-TSMJLLUF","ProcessId":9164,"ThreadId":13,"Application":"Phoenix.Web"}}
{"Timestamp":"2023-01-28T20:19:56.8934347+03:30","Level":"Information","MessageTemplate":"Hosting environment: {envName}","Properties":{"envName":"Development","SourceContext":"Microsoft.Hosting.Lifetime","MachineName":"LAPTOP-TSMJLLUF","ProcessId":9164,"ThreadId":13,"Application":"Phoenix.Web"}}
{"Timestamp":"2023-01-28T20:19:56.8938777+03:30","Level":"Information","MessageTemplate":"Content root path: {contentRoot}","Properties":{"contentRoot":"D:\\MyArchitecture\\Main\\dotnet-phoenix-clean-architecture\\src\\Phoenix.RestApi\\","SourceContext":"Microsoft.Hosting.Lifetime","MachineName":"LAPTOP-TSMJLLUF","ProcessId":9164,"ThreadId":13,"Application":"Phoenix.Web"}}
{"Timestamp":"2023-01-28T20:21:01.1226574+03:30","Level":"Information","MessageTemplate":"Applying Root Migrations ...","Properties":{"SourceContext":"Phoenix.Infrastructure.Persistence.Initialization.DatabaseInitializer","MachineName":"LAPTOP-TSMJLLUF","ProcessId":14024,"ThreadId":13,"Application":"Phoenix.Web"}}
{"Timestamp":"2023-01-28T20:21:04.2894965+03:30","Level":"Information","MessageTemplate":"\r\n*******  | DataBase Migration Updated Successfully | *******\r\n","Properties":{"SourceContext":"Phoenix.Infrastructure.Persistence.Initialization.DatabaseInitializer","MachineName":"LAPTOP-TSMJLLUF","ProcessId":14024,"ThreadId":13,"Application":"Phoenix.Web"}}
{"Timestamp":"2023-01-28T20:21:04.7096963+03:30","Level":"Information","MessageTemplate":"Now listening on: {address}","Properties":{"address":"http://localhost:5000","EventId":{"Id":14,"Name":"ListeningOnAddress"},"SourceContext":"Microsoft.Hosting.Lifetime","MachineName":"LAPTOP-TSMJLLUF","ProcessId":14024,"ThreadId":13,"Application":"Phoenix.Web"}}
{"Timestamp":"2023-01-28T20:21:04.7114318+03:30","Level":"Information","MessageTemplate":"Application started. Press Ctrl+C to shut down.","Properties":{"SourceContext":"Microsoft.Hosting.Lifetime","MachineName":"LAPTOP-TSMJLLUF","ProcessId":14024,"ThreadId":13,"Application":"Phoenix.Web"}}
{"Timestamp":"2023-01-28T20:21:04.7116116+03:30","Level":"Information","MessageTemplate":"Hosting environment: {envName}","Properties":{"envName":"Development","SourceContext":"Microsoft.Hosting.Lifetime","MachineName":"LAPTOP-TSMJLLUF","ProcessId":14024,"ThreadId":13,"Application":"Phoenix.Web"}}
{"Timestamp":"2023-01-28T20:21:04.7117126+03:30","Level":"Information","MessageTemplate":"Content root path: {contentRoot}","Properties":{"contentRoot":"D:\\MyArchitecture\\Main\\dotnet-phoenix-clean-architecture\\src\\Phoenix.RestApi\\","SourceContext":"Microsoft.Hosting.Lifetime","MachineName":"LAPTOP-TSMJLLUF","ProcessId":14024,"ThreadId":13,"Application":"Phoenix.Web"}}
{"Timestamp":"2023-01-28T20:24:51.2338552+03:30","Level":"Information","MessageTemplate":"Applying Root Migrations ...","Properties":{"SourceContext":"Phoenix.Infrastructure.Persistence.Initialization.DatabaseInitializer","MachineName":"LAPTOP-TSMJLLUF","ProcessId":1600,"ThreadId":13,"Application":"Phoenix.Web"}}
{"Timestamp":"2023-01-28T20:24:54.4588510+03:30","Level":"Information","MessageTemplate":"\r\n*******  | DataBase Migration Updated Successfully | *******\r\n","Properties":{"SourceContext":"Phoenix.Infrastructure.Persistence.Initialization.DatabaseInitializer","MachineName":"LAPTOP-TSMJLLUF","ProcessId":1600,"ThreadId":13,"Application":"Phoenix.Web"}}
{"Timestamp":"2023-01-28T20:24:55.0291068+03:30","Level":"Information","MessageTemplate":"Now listening on: {address}","Properties":{"address":"http://localhost:5000","EventId":{"Id":14,"Name":"ListeningOnAddress"},"SourceContext":"Microsoft.Hosting.Lifetime","MachineName":"LAPTOP-TSMJLLUF","ProcessId":1600,"ThreadId":13,"Application":"Phoenix.Web"}}
{"Timestamp":"2023-01-28T20:24:55.0303408+03:30","Level":"Information","MessageTemplate":"Application started. Press Ctrl+C to shut down.","Properties":{"SourceContext":"Microsoft.Hosting.Lifetime","MachineName":"LAPTOP-TSMJLLUF","ProcessId":1600,"ThreadId":13,"Application":"Phoenix.Web"}}
{"Timestamp":"2023-01-28T20:24:55.0305869+03:30","Level":"Information","MessageTemplate":"Hosting environment: {envName}","Properties":{"envName":"Development","SourceContext":"Microsoft.Hosting.Lifetime","MachineName":"LAPTOP-TSMJLLUF","ProcessId":1600,"ThreadId":13,"Application":"Phoenix.Web"}}
{"Timestamp":"2023-01-28T20:24:55.0311280+03:30","Level":"Information","MessageTemplate":"Content root path: {contentRoot}","Properties":{"contentRoot":"D:\\MyArchitecture\\Main\\dotnet-phoenix-clean-architecture\\src\\Phoenix.RestApi\\","SourceContext":"Microsoft.Hosting.Lifetime","MachineName":"LAPTOP-TSMJLLUF","ProcessId":1600,"ThreadId":13,"Application":"Phoenix.Web"}}
{"Timestamp":"2023-01-28T20:25:52.8005874+03:30","Level":"Information","MessageTemplate":"Applying Root Migrations ...","Properties":{"SourceContext":"Phoenix.Infrastructure.Persistence.Initialization.DatabaseInitializer","MachineName":"LAPTOP-TSMJLLUF","ProcessId":22632,"ThreadId":13,"Application":"Phoenix.Web"}}
{"Timestamp":"2023-01-28T20:25:56.0760174+03:30","Level":"Information","MessageTemplate":"\r\n*******  | DataBase Migration Updated Successfully | *******\r\n","Properties":{"SourceContext":"Phoenix.Infrastructure.Persistence.Initialization.DatabaseInitializer","MachineName":"LAPTOP-TSMJLLUF","ProcessId":22632,"ThreadId":13,"Application":"Phoenix.Web"}}
{"Timestamp":"2023-01-28T20:25:56.6690449+03:30","Level":"Information","MessageTemplate":"Now listening on: {address}","Properties":{"address":"http://localhost:5000","EventId":{"Id":14,"Name":"ListeningOnAddress"},"SourceContext":"Microsoft.Hosting.Lifetime","MachineName":"LAPTOP-TSMJLLUF","ProcessId":22632,"ThreadId":13,"Application":"Phoenix.Web"}}
{"Timestamp":"2023-01-28T20:25:56.6719835+03:30","Level":"Information","MessageTemplate":"Application started. Press Ctrl+C to shut down.","Properties":{"SourceContext":"Microsoft.Hosting.Lifetime","MachineName":"LAPTOP-TSMJLLUF","ProcessId":22632,"ThreadId":13,"Application":"Phoenix.Web"}}
{"Timestamp":"2023-01-28T20:25:56.6724994+03:30","Level":"Information","MessageTemplate":"Hosting environment: {envName}","Properties":{"envName":"Development","SourceContext":"Microsoft.Hosting.Lifetime","MachineName":"LAPTOP-TSMJLLUF","ProcessId":22632,"ThreadId":13,"Application":"Phoenix.Web"}}
{"Timestamp":"2023-01-28T20:25:56.6728957+03:30","Level":"Information","MessageTemplate":"Content root path: {contentRoot}","Properties":{"contentRoot":"D:\\MyArchitecture\\Main\\dotnet-phoenix-clean-architecture\\src\\Phoenix.RestApi\\","SourceContext":"Microsoft.Hosting.Lifetime","MachineName":"LAPTOP-TSMJLLUF","ProcessId":22632,"ThreadId":13,"Application":"Phoenix.Web"}}
{"Timestamp":"2023-01-28T20:26:05.6447713+03:30","Level":"Error","MessageTemplate":"Yes Request failed with Status Code 200 and Error Id 751430da-7642-4619-9a83-d91832516667.","Properties":{"StackTrace":"   at Phoenix.RestApi.Controllers.WeatherForecastController.Get() in D:\\MyArchitecture\\Main\\dotnet-phoenix-clean-architecture\\src\\Phoenix.RestApi\\Controllers\\WeatherForecastController.cs:line 12\r\n   at lambda_method21(Closure , Object , Object[] )\r\n   at Microsoft.AspNetCore.Mvc.Infrastructure.ActionMethodExecutor.SyncObjectResultExecutor.Execute(IActionResultTypeMapper mapper, ObjectMethodExecutor executor, Object controller, Object[] arguments)\r\n   at Microsoft.AspNetCore.Mvc.Infrastructure.ControllerActionInvoker.<InvokeActionMethodAsync>g__Logged|12_1(ControllerActionInvoker invoker)\r\n   at Microsoft.AspNetCore.Mvc.Infrastructure.ControllerActionInvoker.<InvokeNextActionFilterAsync>g__Awaited|10_0(ControllerActionInvoker invoker, Task lastTask, State next, Scope scope, Object state, Boolean isCompleted)\r\n   at Microsoft.AspNetCore.Mvc.Infrastructure.ControllerActionInvoker.Rethrow(ActionExecutedContextSealed context)\r\n   at Microsoft.AspNetCore.Mvc.Infrastructure.ControllerActionInvoker.Next(State& next, Scope& scope, Object& state, Boolean& isCompleted)\r\n   at Microsoft.AspNetCore.Mvc.Infrastructure.ControllerActionInvoker.InvokeInnerFilterAsync()\r\n--- End of stack trace from previous location ---\r\n   at Microsoft.AspNetCore.Mvc.Infrastructure.ResourceInvoker.<InvokeFilterPipelineAsync>g__Awaited|20_0(ResourceInvoker invoker, Task lastTask, State next, Scope scope, Object state, Boolean isCompleted)\r\n   at Microsoft.AspNetCore.Mvc.Infrastructure.ResourceInvoker.<InvokeAsync>g__Logged|17_1(ResourceInvoker invoker)\r\n   at Microsoft.AspNetCore.Mvc.Infrastructure.ResourceInvoker.<InvokeAsync>g__Logged|17_1(ResourceInvoker invoker)\r\n   at Microsoft.AspNetCore.Routing.EndpointMiddleware.<Invoke>g__AwaitRequestTask|6_0(Endpoint endpoint, Task requestTask, ILogger logger)\r\n   at Microsoft.AspNetCore.Authorization.AuthorizationMiddleware.Invoke(HttpContext context)\r\n   at Microsoft.AspNetCore.Authentication.AuthenticationMiddleware.Invoke(HttpContext context)\r\n   at Phoenix.Infrastructure.Middleware.ExceptionMiddleware.InvokeAsync(HttpContext context, RequestDelegate next) in D:\\MyArchitecture\\Main\\dotnet-phoenix-clean-architecture\\src\\Phoenix.Infrastructure\\Middleware\\ExceptionMiddleware.cs:line 33","ErrorId":"751430da-7642-4619-9a83-d91832516667","UserEmail":"","RequestId":"0HMO1A24FKNFD:00000002","RequestPath":"/api/v1/tests","ConnectionId":"0HMO1A24FKNFD","MachineName":"LAPTOP-TSMJLLUF","ProcessId":22632,"ThreadId":14,"Application":"Phoenix.Web"}}
